trilium_client/__init__.py
trilium_client/api/__init__.py
trilium_client/api/default_api.py
trilium_client/api_client.py
trilium_client/api_response.py
trilium_client/configuration.py
trilium_client/exceptions.py
trilium_client/models/__init__.py
trilium_client/models/app_info.py
trilium_client/models/attribute.py
trilium_client/models/branch.py
trilium_client/models/create_note_def.py
trilium_client/models/error.py
trilium_client/models/login201_response.py
trilium_client/models/login_request.py
trilium_client/models/note.py
trilium_client/models/note_with_branch.py
trilium_client/models/search_response.py
trilium_client/py.typed
trilium_client/rest.py
trilium_client-0.1.2.dist-info/LICENSE
trilium_client-0.1.2.dist-info/METADATA
trilium_client-0.1.2.dist-info/WHEEL
trilium_client-0.1.2.dist-info/RECORD
