Metadata-Version: 2.3
Name: trilium-client
Version: 0.1.2
Summary: Trilium ETAPI client generated by OpenAPI Generator
Author: mm21
Author-email: mm21.dev@gmail.com
Requires-Python: >=3.7,<4.0
Classifier: Programming Language :: Python :: Implementation :: CPython
Classifier: Operating System :: OS Independent
Classifier: Typing :: Typed
Classifier: Topic :: Software Development :: Libraries :: Python Modules
Classifier: Development Status :: 3 - Alpha
Classifier: Natural Language :: English
Classifier: License :: OSI Approved :: Apache Software License
Classifier: Programming Language :: Python :: 3
Requires-Dist: pydantic (>=2)
Requires-Dist: python-dateutil (>=2.8.2)
Requires-Dist: typing-extensions (>=4.7.1)
Requires-Dist: urllib3 (>=1.25.3,<3.0.0)
Project-URL: Homepage, https://github.com/mm21/trilium-client
